pyfqmr/Simplify.cpython-312-x86_64-linux-gnu.so
pyfqmr/Simplify.h
pyfqmr/Simplify.pyx
pyfqmr/__init__.py
pyfqmr-0.5.0.dist-info/METADATA
pyfqmr-0.5.0.dist-info/WHEEL
pyfqmr-0.5.0.dist-info/top_level.txt
pyfqmr-0.5.0.dist-info/RECORD
pyfqmr-0.5.0.dist-info/licenses/LICENSE
