Metadata-Version: 2.4
Name: pyfqmr
Version: 0.5.0
Summary: cython wrapper around C++ library for fast triangular mesh reduction
Author: kramer84
License: MIT
Project-URL: Homepage, https://github.com/Kramer84/pyfqmr-Fast-quadric-Mesh-Reduction
Classifier: Development Status :: 2 - Pre-Alpha
Classifier: Intended Audience :: Science/Research
Classifier: Operating System :: OS Independent
Classifier: Programming Language :: Python
Classifier: Topic :: Scientific/Engineering
Classifier: License :: OSI Approved :: MIT License
Classifier: Natural Language :: English
License-File: LICENSE
Requires-Dist: numpy
Dynamic: license-file
